codenerix_lib/__init__.py
codenerix_lib/colors.py
codenerix_lib/cryptography.py
codenerix_lib/debugger.py
codenerix_lib/memorytracer.py
codenerix_lib/multiarch.py
codenerix_lib/normalizers.py
codenerix_lib/py.typed
codenerix_lib/pylock.py
codenerix_lib/timeout.py
codenerix_lib-1.0.29.dist-info/LICENSE
codenerix_lib-1.0.29.dist-info/METADATA
codenerix_lib-1.0.29.dist-info/WHEEL
codenerix_lib-1.0.29.dist-info/top_level.txt
codenerix_lib-1.0.29.dist-info/RECORD
