Metadata-Version: 2.1
Name: codenerix-lib
Version: 1.0.29
Summary: Basic libraries used by CODENERIX.
Home-page: https://github.com/codenerix/codenerix-lib
Author: Juanmi Taboada
Author-email: juanmi@juanmitaboada.com
License: Apache License Version 2.0
Keywords: codenerix
Platform: OS Independent
Classifier: Environment :: Web Environment
Classifier: Intended Audience :: Developers
Classifier: License :: Other/Proprietary License
Classifier: Operating System :: OS Independent
Classifier: Programming Language :: Python
Classifier: Programming Language :: Python :: 3
Classifier: Programming Language :: Python :: 3.9
Classifier: Programming Language :: Python :: 3.10
Classifier: Programming Language :: Python :: 3.11
Classifier: Topic :: Internet :: WWW/HTTP
Classifier: Topic :: Internet :: WWW/HTTP :: Dynamic Content
License-File: LICENSE
Requires-Dist: click (==8.1.8)
Requires-Dist: colorama (==0.4.6)
Requires-Dist: joblib (==1.5.0)
Requires-Dist: nltk (==3.9.1)
Requires-Dist: pycryptodomex (==3.22.0)
Requires-Dist: regex (==2024.11.6)
Requires-Dist: textnorm (==1.2)
Requires-Dist: tqdm (==4.67.1)
Requires-Dist: unidecode (==1.4.0)
